cyberdrop_dl/__init__.py
cyberdrop_dl/clients/__init__.py
cyberdrop_dl/clients/download_client.py
cyberdrop_dl/clients/errors.py
cyberdrop_dl/clients/scraper_client.py
cyberdrop_dl/downloader/__init__.py
cyberdrop_dl/downloader/downloader.py
cyberdrop_dl/main.py
cyberdrop_dl/managers/__init__.py
cyberdrop_dl/managers/args_manager.py
cyberdrop_dl/managers/cache_manager.py
cyberdrop_dl/managers/client_manager.py
cyberdrop_dl/managers/config_manager.py
cyberdrop_dl/managers/db_manager.py
cyberdrop_dl/managers/download_manager.py
cyberdrop_dl/managers/log_manager.py
cyberdrop_dl/managers/manager.py
cyberdrop_dl/managers/path_manager.py
cyberdrop_dl/managers/progress_manager.py
cyberdrop_dl/scraper/__init__.py
cyberdrop_dl/scraper/crawler.py
cyberdrop_dl/scraper/crawlers/__init__.py
cyberdrop_dl/scraper/crawlers/bunkrr_crawler.py
cyberdrop_dl/scraper/crawlers/celebforum_crawler.py
cyberdrop_dl/scraper/crawlers/coomer_crawler.py
cyberdrop_dl/scraper/crawlers/cyberdrop_crawler.py
cyberdrop_dl/scraper/crawlers/cyberfile_crawler.py
cyberdrop_dl/scraper/crawlers/ehentai_crawler.py
cyberdrop_dl/scraper/crawlers/erome_crawler.py
cyberdrop_dl/scraper/crawlers/f95zone_crawler.py
cyberdrop_dl/scraper/crawlers/fapello_crawler.py
cyberdrop_dl/scraper/crawlers/gofile_crawler.py
cyberdrop_dl/scraper/crawlers/hotpic_crawler.py
cyberdrop_dl/scraper/crawlers/imageban_crawler.py
cyberdrop_dl/scraper/crawlers/imgbb_crawler.py
cyberdrop_dl/scraper/crawlers/imgbox_crawler.py
cyberdrop_dl/scraper/crawlers/imgkiwi_crawler.py
cyberdrop_dl/scraper/crawlers/imgur_crawler.py
cyberdrop_dl/scraper/crawlers/jpgchurch_crawler.py
cyberdrop_dl/scraper/crawlers/kemono_crawler.py
cyberdrop_dl/scraper/crawlers/leakedmodels_crawler.py
cyberdrop_dl/scraper/crawlers/mediafire_crawler.py
cyberdrop_dl/scraper/crawlers/nudostar_crawler.py
cyberdrop_dl/scraper/crawlers/nudostartv_crawler.py
cyberdrop_dl/scraper/crawlers/omegascans_crawler.py
cyberdrop_dl/scraper/crawlers/pimpandhost_crawler.py
cyberdrop_dl_fix-5.3.37.dist-info/LICENSE
cyberdrop_dl_fix-5.3.37.dist-info/METADATA
cyberdrop_dl_fix-5.3.37.dist-info/WHEEL
cyberdrop_dl_fix-5.3.37.dist-info/entry_points.txt
cyberdrop_dl_fix-5.3.37.dist-info/RECORD
