Metadata-Version: 2.3
Name: cyberdrop-dl-fix
Version: 5.3.37
Summary: Bulk downloader for multiple file hosts
Author: dmcslt
Author-email: dmcslt@gmail.com
Requires-Python: >=3.11,<4.0
Classifier: Programming Language :: Python :: 3
Classifier: Programming Language :: Python :: 3.11
Classifier: Programming Language :: Python :: 3.12
Classifier: Programming Language :: Python :: 3.13
Requires-Dist: aiofiles (==0.8.0)
Requires-Dist: aiohttp (>=3.9.1,<4.0.0)
Requires-Dist: aiolimiter (>=1.1.0,<2.0.0)
Requires-Dist: aiosqlite (==0.17.0)
Requires-Dist: asyncpraw (>=7.7.1,<8.0.0)
Requires-Dist: beautifulsoup4 (>=4.12.2,<5.0.0)
Requires-Dist: browser-cookie3 (>=0.19.1,<0.20.0)
Requires-Dist: certifi (>=2024.2.2,<2025.0.0)
Requires-Dist: filedate (>=3.0,<4.0)
Requires-Dist: get-video-properties (>=0.1.1,<0.2.0)
Requires-Dist: inquirerpy (>=0.3.4,<0.4.0)
Requires-Dist: mediafire (>=0.6.1,<0.7.0)
Requires-Dist: mutagen (>=1.47.0,<2.0.0)
Requires-Dist: myjdapi (>=1.1.7,<2.0.0)
Requires-Dist: pillow (>=10.2.0,<11.0.0)
Requires-Dist: platformdirs (>=4.2.2,<5.0.0)
Requires-Dist: pyyaml (>=6.0.1,<7.0.0)
Requires-Dist: rich (>=13.7.0,<14.0.0)
Project-URL: Documentation, https://jules-winnfieldx.gitbook.io/cyberdrop-dl/
Project-URL: Repository, https://github.com/dmcslt/CyberDropDownloader
